{
  "version": "https://jsonfeed.org/version/1",
  "title": "4thWave AI — Space Tech (Aggregated)",
  "home_page_url": "https://www.4thwaveai.com",
  "feed_url": "https://4thwaveai-feeds.github.io/4thwaveai-feeds/feeds/space-tech.json",
  "items": [
    {
      "id": "https://www.nasa.gov/blogs/spacestation/2026/06/23/nasa-announces-spacewalkers-for-robotic-arm-repair-work/",
      "url": "https://www.nasa.gov/blogs/spacestation/2026/06/23/nasa-announces-spacewalkers-for-robotic-arm-repair-work/",
      "title": "NASA Announces Spacewalkers for Robotic Arm Repair Work - NASA",
      "content_text": "Spacewalk preparations filled the schedule aboard the International Space Station on Tuesday as a pair of astronauts gear up for next week’s external robotics repair job. CubeSat maintenance and eye checks rounded out the day for the Expedition 74 crew.",
      "attachments": [
        {
          "url": "https://images-assets.nasa.gov/image/iss074e0404371/iss074e0404371~large.jpg",
          "mime_type": "image/jpeg"
        }
      ],
      "tags": [
        "space-tech"
      ]
    },
    {
      "id": "https://www.nasa.gov/news/recently-published/",
      "url": "https://www.nasa.gov/news/recently-published/",
      "title": "All NASA News - NASA",
      "content_text": "Stay up-to-date with the latest content from NASA as we explore the universe and discover more about our home planet.",
      "tags": [
        "space-tech"
      ]
    },
    {
      "id": "https://www.nasa.gov/news/media-contacts/",
      "url": "https://www.nasa.gov/news/media-contacts/",
      "title": "NASA Media Contacts - NASA",
      "content_text": "Media Contacts Gerelle DodsonNASA Workforce, STEM Engagement202-358-1600Jennifer DoorenDeputy News Chief, Cybersecurity202-358-1600Alise",
      "attachments": [
        {
          "url": "https://www.nasa.gov/wp-content/uploads/2023/07/52712483677-a4fbc61f0c-k.jpg",
          "mime_type": "image/jpeg"
        }
      ],
      "tags": [
        "space-tech"
      ]
    },
    {
      "id": "https://www.nasa.gov/news/nasa-media-contacts/",
      "url": "https://www.nasa.gov/news/nasa-media-contacts/",
      "title": "NASA Media Contacts - NASA",
      "content_text": "Media Contacts Gerelle DodsonNASA Workforce, STEM Engagement202-358-1600Jennifer DoorenDeputy News Chief, Cybersecurity202-358-1600Alise",
      "attachments": [
        {
          "url": "https://www.nasa.gov/wp-content/uploads/2023/07/52712483677-a4fbc61f0c-k.jpg",
          "mime_type": "image/jpeg"
        }
      ],
      "tags": [
        "space-tech"
      ]
    },
    {
      "id": "https://www.nasa.gov/news/",
      "url": "https://www.nasa.gov/news/",
      "title": "NASA News",
      "content_text": "Resources for news media, including NASA news contacts and archived news material",
      "attachments": [
        {
          "url": "https://www.nasa.gov/wp-content/uploads/2025/05/54492396655-c6ba83df1d-o-1.jpg",
          "mime_type": "image/jpeg"
        }
      ],
      "tags": [
        "space-tech"
      ]
    },
    {
      "id": "https://www.nasa.gov/news-release/nasa-to-cover-us-spacewalk-95-host-preview-news-conference/",
      "url": "https://www.nasa.gov/news-release/nasa-to-cover-us-spacewalk-95-host-preview-news-conference/",
      "title": "NASA to Cover US Spacewalk 95, Host Preview News Conference - NASA",
      "content_text": "NASA astronauts will venture outside the International Space Station on Tuesday, June 30, to replace a wrist joint on the orbital complex’s Canadarm2 robotic",
      "attachments": [
        {
          "url": "https://www.nasa.gov/wp-content/uploads/2026/06/spacewalk-95-advisory-june-22.jpg",
          "mime_type": "image/jpeg"
        }
      ],
      "tags": [
        "space-tech"
      ]
    },
    {
      "id": "https://www.nasa.gov/news-release/nasa-names-sean-gallagher-as-chief-information-officer/",
      "url": "https://www.nasa.gov/news-release/nasa-names-sean-gallagher-as-chief-information-officer/",
      "title": "NASA Names Sean Gallagher as Chief Information Officer - NASA",
      "content_text": "NASA has selected Sean Gallagher as the agency’s chief information officer (CIO). In this role, he is responsible for the agency’s entire portfolio of",
      "attachments": [
        {
          "url": "https://www.nasa.gov/wp-content/uploads/2023/03/gallagher-nasa-2023.jpg",
          "mime_type": "image/jpeg"
        }
      ],
      "tags": [
        "space-tech"
      ]
    },
    {
      "id": "https://www.nasa.gov/news-release/nasa-awards-solutions-for-federal-enterprise-procurement-contracts/",
      "url": "https://www.nasa.gov/news-release/nasa-awards-solutions-for-federal-enterprise-procurement-contracts/",
      "title": "NASA Awards Solutions for Federal Enterprise Procurement Contracts - NASA",
      "content_text": "NASA will begin processing the awards of multiple contracts for the Solutions for Enterprise‑wide Procurement (SEWP) VI Government-wide Acquisition Contract.",
      "attachments": [
        {
          "url": "https://www.nasa.gov/wp-content/uploads/2022/02/nasa_meatball_large.jpg",
          "mime_type": "image/jpeg"
        }
      ],
      "tags": [
        "space-tech"
      ]
    },
    {
      "id": "https://www.nasa.gov/news-release/nasa-invites-media-to-botswana-artemis-accords-signing-ceremony/",
      "url": "https://www.nasa.gov/news-release/nasa-invites-media-to-botswana-artemis-accords-signing-ceremony/",
      "title": "NASA Invites Media to Botswana Artemis Accords Signing Ceremony - NASA",
      "content_text": "The Republic of Botswana will sign the Artemis Accords during a ceremony at 9:30 a.m. EDT Thursday, June 25, at NASA Headquarters in Washington.",
      "attachments": [
        {
          "url": "https://www.nasa.gov/wp-content/uploads/2026/06/nasa-meatball-11-black-background.jpg",
          "mime_type": "image/jpeg"
        }
      ],
      "tags": [
        "space-tech"
      ]
    },
    {
      "id": "https://www.nasa.gov/2026-news-releases/",
      "url": "https://www.nasa.gov/2026-news-releases/",
      "title": "2026 News Releases - NASA",
      "content_text": "Sign up to receive NASA news releases and other information.",
      "attachments": [
        {
          "url": "https://images-assets.nasa.gov/image/NHQ202512200038/NHQ202512200038~large.jpg",
          "mime_type": "image/jpeg"
        }
      ],
      "tags": [
        "space-tech"
      ]
    },
    {
      "id": "https://www.esa.int/Newsroom/Press_Releases/(lang)/en/(year)/2000",
      "url": "https://www.esa.int/Newsroom/Press_Releases/(lang)/en/(year)/2000",
      "title": "Press Releases",
      "content_text": "email: media @ esa.int (Media inquiries only)",
      "tags": [
        "space-tech"
      ]
    },
    {
      "id": "https://www.esa.int/Newsroom/Press_Releases/(lang)/en/(year)/2001",
      "url": "https://www.esa.int/Newsroom/Press_Releases/(lang)/en/(year)/2001",
      "title": "Press Releases",
      "content_text": "email: media @ esa.int (Media inquiries only)",
      "tags": [
        "space-tech"
      ]
    },
    {
      "id": "https://www.esa.int/Newsroom/Press_Releases/(lang)/en/(year)/2002",
      "url": "https://www.esa.int/Newsroom/Press_Releases/(lang)/en/(year)/2002",
      "title": "Press Releases",
      "content_text": "email: media @ esa.int (Media inquiries only)",
      "tags": [
        "space-tech"
      ]
    },
    {
      "id": "https://www.esa.int/Newsroom/Press_Releases/(lang)/en/(year)/2003",
      "url": "https://www.esa.int/Newsroom/Press_Releases/(lang)/en/(year)/2003",
      "title": "Press Releases",
      "content_text": "email: media @ esa.int (Media inquiries only)",
      "tags": [
        "space-tech"
      ]
    },
    {
      "id": "https://www.esa.int/Newsroom/Press_Releases/(lang)/en/(year)/2004",
      "url": "https://www.esa.int/Newsroom/Press_Releases/(lang)/en/(year)/2004",
      "title": "Press Releases",
      "content_text": "email: media @ esa.int (Media inquiries only)",
      "tags": [
        "space-tech"
      ]
    },
    {
      "id": "https://www.esa.int/Newsroom/Press_Releases/(lang)/en/(year)/2005",
      "url": "https://www.esa.int/Newsroom/Press_Releases/(lang)/en/(year)/2005",
      "title": "Press Releases",
      "content_text": "email: media @ esa.int (Media inquiries only)",
      "tags": [
        "space-tech"
      ]
    },
    {
      "id": "https://www.esa.int/Newsroom/Press_Releases/(lang)/cz",
      "url": "https://www.esa.int/Newsroom/Press_Releases/(lang)/cz",
      "title": "Press Releases",
      "content_text": "email: media @ esa.int (Media inquiries only)",
      "tags": [
        "space-tech"
      ]
    },
    {
      "id": "https://www.esa.int/Newsroom/Press_Releases/(lang)/dk",
      "url": "https://www.esa.int/Newsroom/Press_Releases/(lang)/dk",
      "title": "Press Releases",
      "content_text": "email: media @ esa.int (Media inquiries only)",
      "tags": [
        "space-tech"
      ]
    },
    {
      "id": "https://www.esa.int/Newsroom/Press_Releases/(lang)/nl",
      "url": "https://www.esa.int/Newsroom/Press_Releases/(lang)/nl",
      "title": "Press Releases",
      "content_text": "email: media @ esa.int (Media inquiries only)",
      "tags": [
        "space-tech"
      ]
    },
    {
      "id": "https://www.esa.int/Newsroom/Press_Releases/(lang)/ee",
      "url": "https://www.esa.int/Newsroom/Press_Releases/(lang)/ee",
      "title": "Press Releases",
      "content_text": "email: media @ esa.int (Media inquiries only)",
      "tags": [
        "space-tech"
      ]
    },
    {
      "id": "https://www.esa.int/Newsroom/Press_Releases/(lang)/fi",
      "url": "https://www.esa.int/Newsroom/Press_Releases/(lang)/fi",
      "title": "Press Releases",
      "content_text": "email: media @ esa.int (Media inquiries only)",
      "tags": [
        "space-tech"
      ]
    },
    {
      "id": "https://www.esa.int/Newsroom/Press_Releases/(lang)/fr",
      "url": "https://www.esa.int/Newsroom/Press_Releases/(lang)/fr",
      "title": "Press Releases",
      "content_text": "email: media @ esa.int (Uniquement les demandes de la presse)",
      "tags": [
        "space-tech"
      ]
    },
    {
      "id": "https://www.rocketlabusa.com/updates/",
      "url": "https://www.rocketlabusa.com/updates/",
      "title": "News | Rocket Lab",
      "content_text": "Keep up with the latest from Rocket Lab.",
      "attachments": [
        {
          "url": "https://rocketlabcorp.com/themes/base/production/images/og_logo.jpg",
          "mime_type": "image/jpeg"
        }
      ],
      "tags": [
        "space-tech"
      ]
    },
    {
      "id": "https://www.rocketlabusa.com/updates/victus-haze/",
      "url": "https://www.rocketlabusa.com/updates/victus-haze/",
      "title": "Rocket Lab Shatters Responsive Space Record: Launches U.S. Space Force VICTUS HAZE Mission in 16 Hours 42 Minutes | Rocket Lab",
      "content_text": "Historic Speed: Rocket Lab launched the VICTUS HAZE mission just 16 hours and 42 minutes after receiving the U.S. Space Force’s Notice to Launch, beating the previous record by more than 10 hours and setting a new global standard in responsive space access. <br />\nEnd-to-End Space Capability: Marking a…",
      "attachments": [
        {
          "url": "https://rocketlabcorp.com/themes/base/production/images/og_logo.jpg",
          "mime_type": "image/jpeg"
        }
      ],
      "tags": [
        "space-tech"
      ]
    },
    {
      "id": "https://www.rocketlabusa.com/updates/rocket-lab-adds-mars-proven-robotics-capabilities/",
      "url": "https://www.rocketlabusa.com/updates/rocket-lab-adds-mars-proven-robotics-capabilities/",
      "title": "Rocket Lab Adds Mars-Proven Robotics Capabilities with Completion of Motiv Space Systems Acquisition | Rocket Lab",
      "content_text": "Acquisition brings Mars heritage for complex planetary missions, as well as precision mechanisms essential for next-generation space infrastructure including orbital data centers and constellations",
      "attachments": [
        {
          "url": "https://rocketlabcorp.com/themes/base/production/images/og_logo.jpg",
          "mime_type": "image/jpeg"
        }
      ],
      "tags": [
        "space-tech"
      ]
    },
    {
      "id": "https://www.rocketlabusa.com/updates/synspective-launch-nine/",
      "url": "https://www.rocketlabusa.com/updates/synspective-launch-nine/",
      "title": "Mission Success: Rocket Lab Completes 9th Electron Launch for Synspective | Rocket Lab",
      "content_text": "Mahia, New Zealand – Rocket Lab Corporation (Nasdaq: RKLB), a global leader in launch services and space systems, today announced the successful deployment of the latest satellite for Synspective, marking the ninth dedicated mission Rocket Lab has completed for the Japan-based Earth observation…",
      "attachments": [
        {
          "url": "https://rocketlabcorp.com/themes/base/production/images/og_logo.jpg",
          "mime_type": "image/jpeg"
        }
      ],
      "tags": [
        "space-tech"
      ]
    },
    {
      "id": "https://www.rocketlabusa.com/updates/rocket-lab-awarded-90m-contract-to-build-geo-satellites-hosting-space-domain-awareness-payload-for-u-s-space-force/",
      "url": "https://www.rocketlabusa.com/updates/rocket-lab-awarded-90m-contract-to-build-geo-satellites-hosting-space-domain-awareness-payload-for-u-s-space-force/",
      "title": "Rocket Lab Awarded $90M Contract to Build GEO Satellites Hosting Space Domain Awareness Payload for U.S. Space Force  | Rocket Lab",
      "content_text": "Award marks Rocket Lab's first satellite production program for geostationary orbit and continues a Space Systems Command program for development and delivery on orbit of two Heimdall prototype payloads by Rocket Lab Optical Systems.",
      "attachments": [
        {
          "url": "https://rocketlabcorp.com/themes/base/production/images/og_logo.jpg",
          "mime_type": "image/jpeg"
        }
      ],
      "tags": [
        "space-tech"
      ]
    },
    {
      "id": "https://www.rocketlabusa.com/updates/rocket-lab-awarded-30-million-contract-for-haste-hypersonic-rocket-launches-for-anduril/",
      "url": "https://www.rocketlabusa.com/updates/rocket-lab-awarded-30-million-contract-for-haste-hypersonic-rocket-launches-for-anduril/",
      "title": "Rocket Lab Awarded $30 Million Contract for HASTE Hypersonic Rocket Launches for Anduril | Rocket Lab",
      "content_text": "Long Beach, California. May 7, 2026 – Rocket Lab Corporation (Nasdaq: RKLB), a global leader in launch services and space systems, today announced it has been selected by defense technology company Anduril Industries for multiple hypersonic test flights with its HASTE launch vehicle. The…",
      "attachments": [
        {
          "url": "https://rocketlabcorp.com/themes/base/production/images/og_logo.jpg",
          "mime_type": "image/jpeg"
        }
      ],
      "tags": [
        "space-tech"
      ]
    },
    {
      "id": "https://www.relativityspace.com/press-release/2026/6/4/may-2026-company-updatenbspnbsp",
      "url": "https://www.relativityspace.com/press-release/2026/6/4/may-2026-company-updatenbspnbsp",
      "title": "May 2026 Company Update",
      "content_text": "May brought a major milestone for the Terran R program, with the integrated second stage departing Long Beach and beginning its journey to NASA Stennis. Across the company, teams continued advancing work across design, build, test, and launch.   Design  This month, 1,455 flight parts were released,",
      "attachments": [
        {
          "url": "http://static1.squarespace.com/static/59a8fb50d2b8575fad311abb/t/68a4babcbaf5ae7defdb89df/1755626172492/TERRAN_R_LAUNCH.png?format=1500w",
          "mime_type": "image/png"
        },
        {
          "url": "https://www.youtube.com/embed/Mt_bow-eer4",
          "mime_type": "video/mp4"
        }
      ],
      "tags": [
        "space-tech"
      ]
    },
    {
      "id": "https://www.relativityspace.com/press-release/2026/5/8/april-2026-company-update",
      "url": "https://www.relativityspace.com/press-release/2026/5/8/april-2026-company-update",
      "title": "April 2026 Company Update",
      "content_text": "April brought continued momentum across the Terran R program, with progress advancing across design, build, test, and launch.&nbsp;   Design  This month, 2,055 flight parts were released, with a concerted effort on the stage one shipping assembly. Nearly all of the first stage structural compone",
      "attachments": [
        {
          "url": "http://static1.squarespace.com/static/59a8fb50d2b8575fad311abb/t/68a4babcbaf5ae7defdb89df/1755626172492/TERRAN_R_LAUNCH.png?format=1500w",
          "mime_type": "image/png"
        },
        {
          "url": "https://www.youtube.com/embed/VkMOxp9ZKfU",
          "mime_type": "video/mp4"
        }
      ],
      "tags": [
        "space-tech"
      ]
    },
    {
      "id": "https://www.relativityspace.com/press-release/2026/4/13/march-2026-company-updatenbspnbsp",
      "url": "https://www.relativityspace.com/press-release/2026/4/13/march-2026-company-updatenbspnbsp",
      "title": "March 2026 Company Update",
      "content_text": "March brought continued progress across the Terran R program, with key milestones across design, manufacturing, testing, and launch preparations.&nbsp;   Design  This month, the team released 2,207 flight parts, with a continued focus on completing the stage one shipping assembly. Work remains c",
      "attachments": [
        {
          "url": "http://static1.squarespace.com/static/59a8fb50d2b8575fad311abb/t/68a4babcbaf5ae7defdb89df/1755626172492/TERRAN_R_LAUNCH.png?format=1500w",
          "mime_type": "image/png"
        },
        {
          "url": "https://www.youtube.com/embed/MKrGdH-g60w",
          "mime_type": "video/mp4"
        }
      ],
      "tags": [
        "space-tech"
      ]
    },
    {
      "id": "https://www.relativityspace.com/press-release/2026/3/8/february-2026-company-update",
      "url": "https://www.relativityspace.com/press-release/2026/3/8/february-2026-company-update",
      "title": "February 2026 Company Update",
      "content_text": "February marked another month of critical progress across design, build, test, and launch.   Design  This month, the team released an additional 1,826 flight components. The stage two shipping assembly and stage two fluids top-level assembly are now fully released, enabling final integration activit",
      "attachments": [
        {
          "url": "http://static1.squarespace.com/static/59a8fb50d2b8575fad311abb/t/68a4babcbaf5ae7defdb89df/1755626172492/TERRAN_R_LAUNCH.png?format=1500w",
          "mime_type": "image/png"
        },
        {
          "url": "https://www.youtube.com/embed/nVj_hYQxrc8",
          "mime_type": "video/mp4"
        }
      ],
      "tags": [
        "space-tech"
      ]
    }
  ]
}